gadlogger/__init__.py
gadlogger/const/__init__.py
gadlogger/const/logging.py
gadlogger/const/symbols.py
gadlogger/formatters/__init__.py
gadlogger/formatters/base.py
gadlogger/formatters/json.py
gadlogger/formatters/plain.py
gadlogger/mappers/__init__.py
gadlogger/mappers/logging.py
gadlogger/models/__init__.py
gadlogger/models/logging.py
gadlogger/utils/__init__.py
gadlogger/utils/config.py
gadlogger/utils/fields.py
tests/__init__.py
tests/test_init.py
gadlogger-0.0.4.dist-info/LICENSE
gadlogger-0.0.4.dist-info/METADATA
gadlogger-0.0.4.dist-info/WHEEL
gadlogger-0.0.4.dist-info/top_level.txt
gadlogger-0.0.4.dist-info/RECORD
